<?xml version="1.0" encoding="UTF-8"?>
<!-- Tipos de busqueda que se quieren realizar
    1.Por titulo
    2.Por tipo de receta
    3.Por ingredientes
    4.Por nacionalidad de la receta -->
<recetas>
    <receta>
        <titulo>Tortilla de patata</titulo>
        <ingredientes comensales="2">
            <ingrediente nombre="patata" cantidad="1" unidad="kg"></ingrediente>
            <ingrediente nombre="huevo" cantidad="12" unidad="u"></ingrediente>
            <ingrediente nombre="sal" cantidad="3" unidad="cucharada"></ingrediente>
        </ingredientes>
        <general tipo="desayuno" nacionalidad="españa" region="andalucia"></general>
        <procedimiento></procedimiento>
    </receta>
    <receta>
        <titulo>Paella</titulo>
        <ingredientes comensales="4">
            <ingrediente nombre="arroz" cantidad="1" unidad="kg"></ingrediente>
            <ingrediente nombre="pimiento" cantidad="500" unidad="g"></ingrediente>
            <ingrediente nombre="pollo" cantidad="500" unidad="g"></ingrediente>
        </ingredientes>
        <general tipo="cena" nacionalidad="españa" region="valencia"></general>
        <procedimiento></procedimiento>
    </receta>
    <receta>
        <titulo>Bizcocho</titulo>
        <ingredientes comensales="2">
            <ingrediente nombre="harina" cantidad="1" unidad="kg"></ingrediente>
            <ingrediente nombre="leche" cantidad="1" unidad="l"></ingrediente>
            <ingrediente nombre="azucar" cantidad="4" unidad="cucharada"></ingrediente>
        </ingredientes>
        <general tipo="desayuno" nacionalidad="españa" region="madrid"></general>
        <procedimiento></procedimiento>
    </receta>
    <receta>
        <titulo>Hamburguesa</titulo>
        <ingredientes comensales="1">
            <ingrediente nombre="carne" cantidad="300" unidad="g"></ingrediente>
            <ingrediente nombre="pan" cantidad="1" unidad="u"></ingrediente>
            <ingrediente nombre="huevo" cantidad="1" unidad="u"></ingrediente>
            <ingrediente nombre="lechuga" cantidad="1" unidad="u"></ingrediente>
            <ingrediente nombre="tomate" cantidad="1" unidad="u"></ingrediente>
        </ingredientes>
        <general tipo="cena" nacionalidad="usa" region="california"></general>
        <procedimiento></procedimiento>
    </receta>
</recetas>